django_components/__init__.py
django_components/app_settings.py
django_components/apps.py
django_components/attributes.py
django_components/autodiscovery.py
django_components/cache.py
django_components/component.py
django_components/component_media.py
django_components/component_registry.py
django_components/constants.py
django_components/context.py
django_components/dependencies.py
django_components/expression.py
django_components/extension.py
django_components/finders.py
django_components/library.py
django_components/node.py
django_components/provide.py
django_components/py.typed
django_components/slots.py
django_components/tag_formatter.py
django_components/template.py
django_components/template_loader.py
django_components/testing.py
django_components/types.py
django_components/urls.py
django_components/commands/__init__.py
django_components/commands/components.py
django_components/commands/create.py
django_components/commands/ext.py
django_components/commands/ext_list.py
django_components/commands/ext_run.py
django_components/commands/list.py
django_components/commands/startcomponent.py
django_components/commands/upgrade.py
django_components/commands/upgradecomponent.py
django_components/compat/__init__.py
django_components/compat/django.py
django_components/components/__init__.py
django_components/components/dynamic.py
django_components/components/error_fallback.py
django_components/extensions/__init__.py
django_components/extensions/cache.py
django_components/extensions/debug_highlight.py
django_components/extensions/defaults.py
django_components/extensions/dependencies.py
django_components/extensions/view.py
django_components/management/__init__.py
django_components/management/commands/__init__.py
django_components/management/commands/components.py
django_components/management/commands/startcomponent.py
django_components/management/commands/upgradecomponent.py
django_components/perfutil/__init__.py
django_components/perfutil/component.py
django_components-0.143.2.dist-info/licenses/LICENSE
django_components-0.143.2.dist-info/METADATA
django_components-0.143.2.dist-info/WHEEL
django_components-0.143.2.dist-info/top_level.txt
django_components-0.143.2.dist-info/RECORD
