Metadata-Version: 2.4
Name: django_components
Version: 0.143.2
Summary: A way to create simple reusable template components in Django.
Author-email: Emil Stenström <emil@emilstenstrom.se>, Juro Oravec <juraj.oravec.josefson@gmail.com>
License: MIT
Project-URL: Homepage, https://github.com/django-components/django-components/
Project-URL: Documentation, https://django-components.github.io/django-components/
Project-URL: Changelog, https://django-components.github.io/django-components/latest/releases/
Project-URL: Issues, https://github.com/django-components/django-components/issues
Project-URL: Donate, https://github.com/sponsors/EmilStenstrom
Keywords: django,components,css,js,html
Classifier: Framework :: Django
Classifier: Framework :: Django :: 4.2
Classifier: Framework :: Django :: 5.1
Classifier: Framework :: Django :: 5.2
Classifier: Operating System :: OS Independent
Classifier: Programming Language :: Python
Classifier: Programming Language :: Python :: 3
Classifier: Programming Language :: Python :: 3.8
Classifier: Programming Language :: Python :: 3.9
Classifier: Programming Language :: Python :: 3.10
Classifier: Programming Language :: Python :: 3.11
Classifier: Programming Language :: Python :: 3.12
Classifier: Programming Language :: Python :: 3.13
Classifier: Programming Language :: Python :: 3.14
Requires-Python: <4.0,>=3.8
License-File: LICENSE
Requires-Dist: Django>=4.2
Requires-Dist: djc-core-html-parser>=1.0.3
Requires-Dist: typing-extensions>=4.12.2
Dynamic: license-file
